blacknet_os/__init__.py
blacknet_os/core.py
blacknet_os/utils.py
blacknet_os-1.0.dist-info/LICENSE
blacknet_os-1.0.dist-info/METADATA
blacknet_os-1.0.dist-info/WHEEL
blacknet_os-1.0.dist-info/top_level.txt
blacknet_os-1.0.dist-info/RECORD
