Metadata-Version: 2.2
Name: blacknet-os
Version: 1.0
Summary: A hacker OS terminal-based toolset with web browsing, port scanning, reverse shells, and more
Home-page: https://github.com/your-repo
Author: Xscripts Inc.
Author-email: sunnyplaysyt9@gmail.com
Classifier: Programming Language :: Python :: 3
Classifier: License :: OSI Approved :: MIT License
Classifier: Operating System :: OS Independent
Requires-Python: >=3.6
License-File: LICENSE
Dynamic: author
Dynamic: author-email
Dynamic: classifier
Dynamic: description
Dynamic: description-content-type
Dynamic: home-page
Dynamic: requires-python
Dynamic: summary
